kafka_cffi.libs/libcrypto-e9869717.so.1.0.0
kafka_cffi.libs/libz-a147dcb0.so.1.2.3
kafka_cffi.libs/libssl-5a516db1.so.1.0.0
kafka_cffi.libs/librdkafka-2aa5f0cb.so.1
kafka_cffi-0.11.4a10.dist-info/top_level.txt
kafka_cffi-0.11.4a10.dist-info/RECORD
kafka_cffi-0.11.4a10.dist-info/METADATA
kafka_cffi-0.11.4a10.dist-info/LICENSE
kafka_cffi-0.11.4a10.dist-info/WHEEL
kafka_cffi/consumer.py
kafka_cffi/_rdkafka.pypy3-510-x86_64-linux-gnu.so
kafka_cffi/_rdkafka.abi3.so
kafka_cffi/utils.py
kafka_cffi/_rdkafka.pypy3-60-x86_64-linux-gnu.so
kafka_cffi/message.py
kafka_cffi/producer.py
kafka_cffi/__init__.py
kafka_cffi/enums.py
kafka_cffi/errors.py
kafka_cffi/client.py
