Metadata-Version: 2.1
Name: kafka-cffi
Version: 0.11.4a10
Summary: A CFFI binding for librdkafka
Home-page: https://github.com/wenxiang/cffi_kafka
Author: Wenxiang Wu
Author-email: thewrongboy@gmail.com
License: MIT
Platform: UNKNOWN
Requires-Dist: cffi (>=1.0.0)
Requires-Dist: six
